audio2dataset/__init__.py
audio2dataset/distributor.py
audio2dataset/downloader.py
audio2dataset/logger.py
audio2dataset/main.py
audio2dataset/reader.py
audio2dataset/subsampler.py
audio2dataset/writer.py
audio2dataset-1.0.1.data/data/README.md
audio2dataset-1.0.1.dist-info/LICENSE
audio2dataset-1.0.1.dist-info/METADATA
audio2dataset-1.0.1.dist-info/WHEEL
audio2dataset-1.0.1.dist-info/entry_points.txt
audio2dataset-1.0.1.dist-info/top_level.txt
audio2dataset-1.0.1.dist-info/RECORD
