Metadata-Version: 2.1
Name: audio2dataset
Version: 1.0.1
Summary: A python template
Home-page: https://github.com/rom1504/audio2dataset
Author: Romain Beaumont
Author-email: romain.rom1@gmail.com
License: MIT
Keywords: machine learning
Platform: UNKNOWN
Classifier: Development Status :: 4 - Beta
Classifier: Intended Audience :: Developers
Classifier: Topic :: Scientific/Engineering :: Artificial Intelligence
Classifier: License :: OSI Approved :: MIT License
Classifier: Programming Language :: Python :: 3.6
Requires-Dist: tqdm (<5,>=4.62.3)
Requires-Dist: fire (<0.5.0,>=0.4.0)
Requires-Dist: webdataset (<0.2,>=0.1.103)
Requires-Dist: pandas (<2,>=1.1.5)
Requires-Dist: pyarrow (<8,>=6.0.1)
Requires-Dist: dataclasses (<1.0.0,>=0.6)
Requires-Dist: wandb (<0.13,>=0.12.10)
Requires-Dist: fsspec (==2022.1.0)
